<?xml version="1.0" encoding="euc-kr"?>
<WORLD ID="w_960100_MH">
  <GSAPATH>../Data/3_World/93_EventMap/600_monsterhunt/960100_MH.gsa</GSAPATH>
  <MINIMAP Y="110" H="250">../Data/3_World/93_EventMap/600_monsterhunt/960100_MM.dds</MINIMAP>
  <BGSOUND VOLUME="0.7">../BGM/Akia.BGM.mp3</BGSOUND>
  <BLOOM BLUR="0.85" BRIGHT="20.4" SRC="0.7" GLOW="0.35" HIGHLIGHT="0.02" />
  <MAX_SPAWN_LOCATION COUNT="8"/>
  <SPAWN_COUNT_PER_LOCATION COUNT="5"/>


	<WORLDEVENT_OBJECT_LIST>			

		<WORLDEVENT_OBJECT ID="1" INIT_STATE="0" TYPE="PUPPET" NAME="TCGroundGate1001_01 01"/> 
		<WORLDEVENT_OBJECT ID="2" INIT_STATE="0" TYPE="PUPPET" NAME="TCGroundGate1001_01 02"/> 
		<WORLDEVENT_OBJECT ID="3" INIT_STATE="0" TYPE="PUPPET" NAME="TCGroundGate1001_01 03"/> 
		<WORLDEVENT_OBJECT ID="4" INIT_STATE="0" TYPE="PUPPET" NAME="TCGroundGate1001_01 04"/> 
		<WORLDEVENT_OBJECT ID="5" INIT_STATE="0" TYPE="PUPPET" NAME="TCGroundGate1001_01 05"/>
		<WORLDEVENT_OBJECT ID="6" INIT_STATE="0" TYPE="PUPPET" NAME="TCGroundGate1001_01 06"/> 
		<WORLDEVENT_OBJECT ID="7" INIT_STATE="0" TYPE="PUPPET" NAME="TCGroundGate1001_01 07"/>
		<WORLDEVENT_OBJECT ID="8" INIT_STATE="0" TYPE="PUPPET" NAME="TCGroundGate1001_01 08"/> 

		<!--바닥화살표 이펙트 제어-->
		<WORLDEVENT_OBJECT ID="11" INIT_STATE="0" INIT_SHOW="0" TYPE="MAPOBJECT" NAME="ArrowSign1001_01 01"/>	
		<WORLDEVENT_OBJECT ID="12" INIT_STATE="0" INIT_SHOW="0" TYPE="MAPOBJECT" NAME="ArrowSign1001_01 02"/>	
		<WORLDEVENT_OBJECT ID="13" INIT_STATE="0" INIT_SHOW="0" TYPE="MAPOBJECT" NAME="ArrowSign1001_01 03"/>	
		<WORLDEVENT_OBJECT ID="14" INIT_STATE="0" INIT_SHOW="0" TYPE="MAPOBJECT" NAME="ArrowSign1001_01 04"/>
		<WORLDEVENT_OBJECT ID="15" INIT_STATE="0" INIT_SHOW="0" TYPE="MAPOBJECT" NAME="ArrowSign1001_01 05"/>	
		<WORLDEVENT_OBJECT ID="16" INIT_STATE="0" INIT_SHOW="0" TYPE="MAPOBJECT" NAME="ArrowSign1001_01 06"/>	
		<WORLDEVENT_OBJECT ID="17" INIT_STATE="0" INIT_SHOW="0" TYPE="MAPOBJECT" NAME="ArrowSign1001_01 07"/>	
		<WORLDEVENT_OBJECT ID="18" INIT_STATE="0" INIT_SHOW="0" TYPE="MAPOBJECT" NAME="ArrowSign1001_01 08"/>

		
	</WORLDEVENT_OBJECT_LIST>

	<WORLD_EVENT ID="1" ENABLE="1">
		<CONDITION BINDING="AND" TARGET_TYPE="EVENT_GROUND_STATE" TARGET_ID="0" EVENT="EQUAL" VALUE="4" /> <!-- 4 : EGS_PLAY 이벤트 실행 -->
		<ACTIVATE_ACTION>
			<ACTION TARGET_TYPE="CLIENT_OBJECT" TARGET_ID="1" EVENT="STATUS" VALUE="1"/>
			<ACTION TARGET_TYPE="CLIENT_OBJECT" TARGET_ID="2" EVENT="STATUS" VALUE="1"/>
			<ACTION TARGET_TYPE="CLIENT_OBJECT" TARGET_ID="3" EVENT="STATUS" VALUE="1"/>
			<ACTION TARGET_TYPE="CLIENT_OBJECT" TARGET_ID="4" EVENT="STATUS" VALUE="1"/>	
			<ACTION TARGET_TYPE="CLIENT_OBJECT" TARGET_ID="5" EVENT="STATUS" VALUE="1"/>
			<ACTION TARGET_TYPE="CLIENT_OBJECT" TARGET_ID="6" EVENT="STATUS" VALUE="1"/>
			<ACTION TARGET_TYPE="CLIENT_OBJECT" TARGET_ID="7" EVENT="STATUS" VALUE="1"/>
			<ACTION TARGET_TYPE="CLIENT_OBJECT" TARGET_ID="8" EVENT="STATUS" VALUE="1"/>
		</ACTIVATE_ACTION>
		<DEACTIVATE_ACTION>
			<ACTION TARGET_TYPE="CLIENT_OBJECT" TARGET_ID="1" EVENT="STATUS" VALUE="0"/>
			<ACTION TARGET_TYPE="CLIENT_OBJECT" TARGET_ID="2" EVENT="STATUS" VALUE="0"/>
			<ACTION TARGET_TYPE="CLIENT_OBJECT" TARGET_ID="3" EVENT="STATUS" VALUE="0"/>
			<ACTION TARGET_TYPE="CLIENT_OBJECT" TARGET_ID="4" EVENT="STATUS" VALUE="0"/>	
			<ACTION TARGET_TYPE="CLIENT_OBJECT" TARGET_ID="5" EVENT="STATUS" VALUE="0"/>
			<ACTION TARGET_TYPE="CLIENT_OBJECT" TARGET_ID="6" EVENT="STATUS" VALUE="0"/>
			<ACTION TARGET_TYPE="CLIENT_OBJECT" TARGET_ID="7" EVENT="STATUS" VALUE="0"/>
			<ACTION TARGET_TYPE="CLIENT_OBJECT" TARGET_ID="8" EVENT="STATUS" VALUE="0"/>	
			<ACTION TARGET_TYPE="WORLD_EVENT" TARGET_ID="4" EVENT="STATUS" VALUE="0"/>
		</DEACTIVATE_ACTION>
	</WORLD_EVENT>


	<WORLD_EVENT ID="2" ENABLE="1">
		<CONDITION BINDING="AND" TARGET_TYPE="WORLD_EVENT" TARGET_ID="1" EVENT="ACT_AFTER_TIME" VALUE="1500" />	<!-- 문열리고 1.5초 뒤-->
			<ACTIVATE_ACTION>
				<ACTION TARGET_TYPE="CLIENT_OBJECT" TARGET_ID="11" EVENT="SHOW" VALUE="1"/> <!--바닥화살표 -->
				<ACTION TARGET_TYPE="CLIENT_OBJECT" TARGET_ID="12" EVENT="SHOW" VALUE="1"/> <!--바닥화살표 -->
				<ACTION TARGET_TYPE="CLIENT_OBJECT" TARGET_ID="13" EVENT="SHOW" VALUE="1"/> <!--바닥화살표 -->
				<ACTION TARGET_TYPE="CLIENT_OBJECT" TARGET_ID="14" EVENT="SHOW" VALUE="1"/> <!--바닥화살표 -->
				<ACTION TARGET_TYPE="CLIENT_OBJECT" TARGET_ID="15" EVENT="SHOW" VALUE="1"/> <!--바닥화살표 -->
				<ACTION TARGET_TYPE="CLIENT_OBJECT" TARGET_ID="16" EVENT="SHOW" VALUE="1"/> <!--바닥화살표 -->
				<ACTION TARGET_TYPE="CLIENT_OBJECT" TARGET_ID="17" EVENT="SHOW" VALUE="1"/> <!--바닥화살표 -->
				<ACTION TARGET_TYPE="CLIENT_OBJECT" TARGET_ID="18" EVENT="SHOW" VALUE="1"/> <!--바닥화살표 -->
			</ACTIVATE_ACTION>
	</WORLD_EVENT>

	
	<WORLD_EVENT ID="3" ENABLE="1">
		<CONDITION BINDING="AND" TARGET_TYPE="WORLD_EVENT" TARGET_ID="2" EVENT="ACT_AFTER_TIME" VALUE="15000" />	<!-- 문열리고 15초 뒤-->
			<ACTIVATE_ACTION>
				<ACTION TARGET_TYPE="CLIENT_OBJECT" TARGET_ID="11" EVENT="SHOW" VALUE="0"/> <!--바닥화살표 -->
				<ACTION TARGET_TYPE="CLIENT_OBJECT" TARGET_ID="12" EVENT="SHOW" VALUE="0"/> <!--바닥화살표 -->
				<ACTION TARGET_TYPE="CLIENT_OBJECT" TARGET_ID="13" EVENT="SHOW" VALUE="0"/> <!--바닥화살표 -->
				<ACTION TARGET_TYPE="CLIENT_OBJECT" TARGET_ID="14" EVENT="SHOW" VALUE="0"/> <!--바닥화살표 -->
				<ACTION TARGET_TYPE="CLIENT_OBJECT" TARGET_ID="15" EVENT="SHOW" VALUE="0"/> <!--바닥화살표 -->
				<ACTION TARGET_TYPE="CLIENT_OBJECT" TARGET_ID="16" EVENT="SHOW" VALUE="0"/> <!--바닥화살표 -->
				<ACTION TARGET_TYPE="CLIENT_OBJECT" TARGET_ID="17" EVENT="SHOW" VALUE="0"/> <!--바닥화살표 -->
				<ACTION TARGET_TYPE="CLIENT_OBJECT" TARGET_ID="18" EVENT="SHOW" VALUE="0"/> <!--바닥화살표 -->
			</ACTIVATE_ACTION>
	</WORLD_EVENT>

	<WORLD_EVENT ID="4" ENABLE="1">
		<CONDITION BINDING="AND" TARGET_TYPE="EVENT_GROUND_STATE" TARGET_ID="0" EVENT="EQUAL" VALUE="64" /> <!--16 : EGS_END 이벤트 실행 -->
		<ACTIVATE_ACTION>
			<ACTION TARGET_TYPE="WORLD_EVENT" TARGET_ID="1" EVENT="STATUS" VALUE="0"/>
		</ACTIVATE_ACTION>
	</WORLD_EVENT>
  
	<!--8방향 설정-->
	<FREE_DIRECTION ALL="TRUE"/>
	<BLOOM BLUR="1.5" BRIGHT="10.0" SRC="0.7" GLOW="0.35" HIGHLIGHT="1.0"/>

<!--카메라--> 
    <CAMERA_ADJUST ZOOM="50" UP="80" TARGET_Z="50" />
	<CAMERA_ADJUST WHEEL_MIN_ZOOM="1" WHEEL_MAX_ZOOM="1.5"/>
  

</WORLD>