<?xml version="1.0" encoding="euc-kr"?>
<!-- edited with XMLSpy v2006 U (http://www.altova.com) by user1 (EMBRACE) -->
<!-- edited with XML Spy v4.4 U (http://www.xmlspy.com) by kkj (kkj) -->
<QUEST>
	<ID>3409</ID>
	<GROUPNO>0</GROUPNO>
	<TITLE TEXT="518909">비밀 장소 침투</TITLE>
	<GROUPNAME TEXT="501265">배신자의 고개</GROUPNAME>
	<LIMITS>
		<LEVEL MIN="33" MAX="42"/>
		<CLASSES>
			<CLASS MEMO="Fighter">1</CLASS>
			<CLASS MEMO="Magician">2</CLASS>
			<CLASS MEMO="Archer">3</CLASS>
			<CLASS MEMO="Thief">4</CLASS>
			<CLASS MEMO="Knight">5</CLASS>
			<CLASS MEMO="Warrior">6</CLASS>
			<CLASS MEMO="Mage">7</CLASS>
			<CLASS MEMO="Battle Bame">8</CLASS>
			<CLASS MEMO="Hunter">9</CLASS>
			<CLASS MEMO="Ranger">10</CLASS>
			<CLASS MEMO="Clown">11</CLASS>
			<CLASS MEMO="Assassin">12</CLASS>
			<CLASS MEMO="Paladin">13</CLASS>
			<CLASS MEMO="Gladiator">14</CLASS>
			<CLASS MEMO="Wizard">15</CLASS>
			<CLASS MEMO="War Mage">16</CLASS>
			<CLASS MEMO="Trapper">17</CLASS>
			<CLASS MEMO="Sniper">18</CLASS>
			<CLASS MEMO="Dancer">19</CLASS>
			<CLASS MEMO="Ninja">20</CLASS>
			<CLASS MEMO="Dragoon">21</CLASS>
			<CLASS MEMO="Destroyer">22</CLASS>
			<CLASS MEMO="Archmage">23</CLASS>
			<CLASS MEMO="War Lord">24</CLASS>
			<CLASS MEMO="Sentinel">25</CLASS>
			<CLASS MEMO="Launcher">26</CLASS>
			<CLASS MEMO="Free Jacker">27</CLASS>
			<CLASS MEMO="Shadow">28</CLASS>
			<CLASS MEMO="Duelist">29</CLASS>
			<CLASS MEMO="Doctor">30</CLASS>
			<CLASS MEMO="Gun Slinger">31</CLASS>
			<CLASS MEMO="Bard">32</CLASS>
			<CLASS MEMO="Battle Master">33</CLASS>
			<CLASS MEMO="Anatomist">34</CLASS>
			<CLASS MEMO="Desperado">35</CLASS>
			<CLASS MEMO="Vocal">36</CLASS>
		</CLASSES>
		<!--<ITEMS>
			<ITEM COUNT="0">9100000</ITEM>
		</ITEMS> -->
		<QUESTS>
			<QUEST>3408</QUEST>
			<QUEST>0</QUEST>
		</QUESTS>
		<LOCATIONS>
			<!-- <LOCATION>2</LOCATION>-->
		</LOCATIONS>
		<PARTY MIN="1" MAX="1"/>
	</LIMITS>
	<CLIENTS>
		<CLIENT TYPE="NPC" EVENTNO="10000">C37A7B4D-AD90-4c81-B1A3-4EBAAF9C8AC7</CLIENT>
	</CLIENTS>
	<AGENTS>
		<AGENT TYPE="NPC" EVENTNO="10002">C37A7B4D-AD90-4c81-B1A3-4EBAAF9C8AC7</AGENT>
	</AGENTS>
	<PAYERS>
		<PAYER TYPE="NPC" EVENTNO="10003">C37A7B4D-AD90-4c81-B1A3-4EBAAF9C8AC7</PAYER>
	</PAYERS>
	<EVENTS>
		<NPC OBJECTNO="0" TYPE="CLIENT" VALUE="101">10000</NPC>
		<NPC OBJECTNO="0" TYPE="ING_DLG" VALUE="501">10002</NPC>
		<NPC OBJECTNO="0" TYPE="PAYER" VALUE="601">10003</NPC>
		<!--굶주린 갈색늑대 -->
		<MONSTER OBJECTNO="1" TYPE="INCPARAM_IN" VALUE="9013300/1">6004100</MONSTER>
		<MONSTER OBJECTNO="1" TYPE="INCPARAM_IN" VALUE="9013300/1">6004101</MONSTER>
		<MONSTER OBJECTNO="1" TYPE="INCPARAM_IN" VALUE="9013300/1">60041001</MONSTER>
		<MONSTER OBJECTNO="1" TYPE="INCPARAM_IN" VALUE="9013300/1">6004102</MONSTER>
		<MONSTER OBJECTNO="1" TYPE="INCPARAM_IN" VALUE="9013300/1">6004103</MONSTER>
		<MONSTER OBJECTNO="1" TYPE="INCPARAM_IN" VALUE="9013300/1">6004104</MONSTER>
		<MONSTER OBJECTNO="1" TYPE="INCPARAM_IN" VALUE="9013300/1">6004106</MONSTER>
		<MONSTER OBJECTNO="1" TYPE="INCPARAM_IN" VALUE="9013300/1">6004105</MONSTER>
		<MONSTER OBJECTNO="1" TYPE="INCPARAM_IN" VALUE="9013300/1">6004107</MONSTER>
		<MONSTER OBJECTNO="1" TYPE="INCPARAM_IN" VALUE="9013300/1">6004108</MONSTER>
		<MONSTER OBJECTNO="1" TYPE="INCPARAM_IN" VALUE="9013300/1">6004124</MONSTER>
		<MONSTER OBJECTNO="1" TYPE="INCPARAM_IN" VALUE="9013300/1">6004142</MONSTER>
		<MONSTER OBJECTNO="1" TYPE="INCPARAM_IN" VALUE="9013300/1">6004144</MONSTER>
		<MONSTER OBJECTNO="1" TYPE="INCPARAM_IN" VALUE="9013300/1">6004148</MONSTER>
		<MONSTER OBJECTNO="1" TYPE="INCPARAM_IN" VALUE="9013300/1">6004146</MONSTER>
		<MONSTER OBJECTNO="1" TYPE="INCPARAM_IN" VALUE="9013300/1">6004145</MONSTER>
		<MONSTER OBJECTNO="1" TYPE="INCPARAM_IN" VALUE="9013300/1">6004149</MONSTER>
		<MONSTER OBJECTNO="1" TYPE="INCPARAM_IN" VALUE="9013300/1">6004150</MONSTER>
		<MONSTER OBJECTNO="1" TYPE="INCPARAM_IN" VALUE="9013300/1">6004125</MONSTER>
		<MONSTER OBJECTNO="1" TYPE="INCPARAM_IN" VALUE="9013300/1">6004300</MONSTER>
		<MONSTER OBJECTNO="1" TYPE="INCPARAM_IN" VALUE="9013300/1">6004304</MONSTER>
		<MONSTER OBJECTNO="1" TYPE="INCPARAM_IN" VALUE="9013300/1">6004305</MONSTER>
		<MONSTER OBJECTNO="1" TYPE="INCPARAM_IN" VALUE="9013300/1">6004306</MONSTER>
		<MONSTER OBJECTNO="1" TYPE="INCPARAM_IN" VALUE="9013300/1">6004307</MONSTER>
		<MONSTER OBJECTNO="1" TYPE="INCPARAM_IN" VALUE="9013300/1">6004308</MONSTER>
		<MONSTER OBJECTNO="1" TYPE="INCPARAM_IN" VALUE="9013300/1">6004309</MONSTER>
		<MONSTER OBJECTNO="1" TYPE="INCPARAM_IN" VALUE="9013300/1">6004325</MONSTER>
		<MONSTER OBJECTNO="1" TYPE="INCPARAM_IN" VALUE="9013300/1">6004324</MONSTER>
		<MONSTER OBJECTNO="1" TYPE="INCPARAM_IN" VALUE="9013300/1">6004349</MONSTER>
		<MONSTER OBJECTNO="1" TYPE="INCPARAM_IN" VALUE="9013300/1">6004348</MONSTER>
		<MONSTER OBJECTNO="1" TYPE="INCPARAM_IN" VALUE="9013300/1">6004347</MONSTER>
		<MONSTER OBJECTNO="1" TYPE="INCPARAM_IN" VALUE="9013300/1">6004350</MONSTER>
		<MONSTER OBJECTNO="1" TYPE="INCPARAM_IN" VALUE="9013300/1">6004321</MONSTER>
		<MONSTER OBJECTNO="1" TYPE="INCPARAM_IN" VALUE="9013300/1">6004351</MONSTER>
		<MONSTER OBJECTNO="1" TYPE="INCPARAM_IN" VALUE="9013300/1">6004202</MONSTER>
		<MONSTER OBJECTNO="1" TYPE="INCPARAM_IN" VALUE="9013300/1">6004203</MONSTER>
		<MONSTER OBJECTNO="1" TYPE="INCPARAM_IN" VALUE="9013300/1">6004204</MONSTER>
		<MONSTER OBJECTNO="1" TYPE="INCPARAM_IN" VALUE="9013300/1">6004205</MONSTER>
		<MONSTER OBJECTNO="1" TYPE="INCPARAM_IN" VALUE="9013300/1">6004206</MONSTER>
		<MONSTER OBJECTNO="1" TYPE="INCPARAM_IN" VALUE="9013300/1">6004207</MONSTER>
		<MONSTER OBJECTNO="1" TYPE="INCPARAM_IN" VALUE="9013300/1">6004208</MONSTER>
		<MONSTER OBJECTNO="1" TYPE="INCPARAM_IN" VALUE="9013300/1">6004242</MONSTER>
		<MONSTER OBJECTNO="1" TYPE="INCPARAM_IN" VALUE="9013300/1">6004245</MONSTER>
		<MONSTER OBJECTNO="1" TYPE="INCPARAM_IN" VALUE="9013300/1">6004225</MONSTER>
		<MONSTER OBJECTNO="1" TYPE="INCPARAM_IN" VALUE="9013300/1">6004246</MONSTER>
		<MONSTER OBJECTNO="1" TYPE="INCPARAM_IN" VALUE="9013300/1">6004243</MONSTER>
		<MONSTER OBJECTNO="1" TYPE="INCPARAM_IN" VALUE="9013300/1">6004248</MONSTER>
		<MONSTER OBJECTNO="1" TYPE="INCPARAM_IN" VALUE="9013300/1">6004251</MONSTER>
		<MONSTER OBJECTNO="1" TYPE="INCPARAM_IN" VALUE="9013300/1">6004250</MONSTER>
		<MONSTER OBJECTNO="1" TYPE="INCPARAM_IN" VALUE="9013300/1">6004249</MONSTER>
		<MONSTER OBJECTNO="1" TYPE="INCPARAM_IN" VALUE="9013300/1">6004247</MONSTER>
		<MONSTER OBJECTNO="1" TYPE="INCPARAM_IN" VALUE="9013300/1">6004222</MONSTER>
		<MONSTER OBJECTNO="1" TYPE="INCPARAM_IN" VALUE="9013300/1">6048223</MONSTER>
		<MONSTER OBJECTNO="1" TYPE="INCPARAM_IN" VALUE="9013300/1">6048247</MONSTER>
		<MONSTER OBJECTNO="1" TYPE="INCPARAM_IN" VALUE="9013300/1">6048250</MONSTER>
		<MONSTER OBJECTNO="1" TYPE="INCPARAM_IN" VALUE="9013300/1">6048246</MONSTER>
		<MONSTER OBJECTNO="1" TYPE="INCPARAM_IN" VALUE="9013300/1">6048254</MONSTER>
		<MONSTER OBJECTNO="1" TYPE="INCPARAM_IN" VALUE="9013300/1">6048248</MONSTER>
		<MONSTER OBJECTNO="1" TYPE="INCPARAM_IN" VALUE="9013300/1">6048251</MONSTER>
		<MONSTER OBJECTNO="1" TYPE="INCPARAM_IN" VALUE="9013300/1">6048252</MONSTER>
		<MONSTER OBJECTNO="1" TYPE="INCPARAM_IN" VALUE="9013300/1">6048258</MONSTER>
		<MONSTER OBJECTNO="1" TYPE="INCPARAM_IN" VALUE="9013300/1">8048261</MONSTER>
		<MONSTER OBJECTNO="1" TYPE="INCPARAM_IN" VALUE="9013300/1">8048262</MONSTER>
		<MONSTER OBJECTNO="1" TYPE="INCPARAM_IN" VALUE="9013300/1">8048263</MONSTER>
		<MONSTER OBJECTNO="1" TYPE="INCPARAM_IN" VALUE="9013300/1">8048264</MONSTER>
		<MONSTER OBJECTNO="1" TYPE="INCPARAM_IN" VALUE="9013300/1">8048269</MONSTER>
		<MONSTER OBJECTNO="1" TYPE="INCPARAM_IN" VALUE="9013300/1">8048265</MONSTER>
		<MONSTER OBJECTNO="1" TYPE="INCPARAM_IN" VALUE="9013300/1">8048272</MONSTER>
		<MONSTER OBJECTNO="1" TYPE="INCPARAM_IN" VALUE="9013300/1">6048122</MONSTER>
		<MONSTER OBJECTNO="1" TYPE="INCPARAM_IN" VALUE="9013300/1">6048145</MONSTER>
		<MONSTER OBJECTNO="1" TYPE="INCPARAM_IN" VALUE="9013300/1">6048146</MONSTER>
		<MONSTER OBJECTNO="1" TYPE="INCPARAM_IN" VALUE="9013300/1">6048149</MONSTER>
		<MONSTER OBJECTNO="1" TYPE="INCPARAM_IN" VALUE="9013300/1">6048147</MONSTER>
		<MONSTER OBJECTNO="1" TYPE="INCPARAM_IN" VALUE="9013300/1">6048150</MONSTER>
		<MONSTER OBJECTNO="1" TYPE="INCPARAM_IN" VALUE="9013300/1">6048151</MONSTER>
		<MONSTER OBJECTNO="1" TYPE="INCPARAM_IN" VALUE="9013300/1">6048153</MONSTER>
		<MONSTER OBJECTNO="1" TYPE="INCPARAM_IN" VALUE="9013300/1">6048154</MONSTER>
		<MONSTER OBJECTNO="1" TYPE="INCPARAM_IN" VALUE="9013300/1">8048161</MONSTER>
		<MONSTER OBJECTNO="1" TYPE="INCPARAM_IN" VALUE="9013300/1">8048162</MONSTER>
		<MONSTER OBJECTNO="1" TYPE="INCPARAM_IN" VALUE="9013300/1">8048163</MONSTER>
		<MONSTER OBJECTNO="1" TYPE="INCPARAM_IN" VALUE="9013300/1">8048164</MONSTER>
		<MONSTER OBJECTNO="1" TYPE="INCPARAM_IN" VALUE="9013300/1">8048165</MONSTER>
		<MONSTER OBJECTNO="1" TYPE="INCPARAM_IN" VALUE="9013300/1">8048169</MONSTER>
		<MONSTER OBJECTNO="1" TYPE="INCPARAM_IN" VALUE="9013300/1">8048170</MONSTER>
		<MONSTER OBJECTNO="1" TYPE="INCPARAM_IN" VALUE="9013300/1">8048171</MONSTER>
		<MONSTER OBJECTNO="1" TYPE="INCPARAM_IN" VALUE="9013300/1">6002305</MONSTER>
		<MONSTER OBJECTNO="1" TYPE="INCPARAM_IN" VALUE="9013300/1">6002306</MONSTER>
		<MONSTER OBJECTNO="1" TYPE="INCPARAM_IN" VALUE="9013300/1">6002308</MONSTER>
		<MONSTER OBJECTNO="1" TYPE="INCPARAM_IN" VALUE="9013300/1">6002309</MONSTER>
		<MONSTER OBJECTNO="1" TYPE="INCPARAM_IN" VALUE="9013300/1">6002311</MONSTER>
		<MONSTER OBJECTNO="1" TYPE="INCPARAM_IN" VALUE="9013300/1">6002312</MONSTER>
		<MONSTER OBJECTNO="1" TYPE="INCPARAM_IN" VALUE="9013300/1">6002348</MONSTER>
		<MONSTER OBJECTNO="1" TYPE="INCPARAM_IN" VALUE="9013300/1">6002347</MONSTER>
		<MONSTER OBJECTNO="1" TYPE="INCPARAM_IN" VALUE="9013300/1">6002349</MONSTER>
		<MONSTER OBJECTNO="1" TYPE="INCPARAM_IN" VALUE="9013300/1">6002350</MONSTER>
		<MONSTER OBJECTNO="1" TYPE="INCPARAM_IN" VALUE="9013300/1">6002351</MONSTER>
		<MONSTER OBJECTNO="1" TYPE="INCPARAM_IN" VALUE="9013300/1">6040121</MONSTER>
		<MONSTER OBJECTNO="1" TYPE="INCPARAM_IN" VALUE="9013300/1">6040154</MONSTER>
		<MONSTER OBJECTNO="1" TYPE="INCPARAM_IN" VALUE="9013300/1">6040156</MONSTER>
		<MONSTER OBJECTNO="1" TYPE="INCPARAM_IN" VALUE="9013300/1">6040158</MONSTER>
		<MONSTER OBJECTNO="1" TYPE="INCPARAM_IN" VALUE="9013300/1">6040150</MONSTER>
		<MONSTER OBJECTNO="1" TYPE="INCPARAM_IN" VALUE="9013300/1">6040160</MONSTER>
		<MONSTER OBJECTNO="1" TYPE="INCPARAM_IN" VALUE="9013300/1">6040161</MONSTER>
		<MONSTER OBJECTNO="1" TYPE="INCPARAM_IN" VALUE="9013300/1">6040166</MONSTER>
		<MONSTER OBJECTNO="1" TYPE="INCPARAM_IN" VALUE="9013300/1">6040194</MONSTER>
		<MONSTER OBJECTNO="1" TYPE="INCPARAM_IN" VALUE="9013300/1">6040196</MONSTER>
		<MONSTER OBJECTNO="1" TYPE="INCPARAM_IN" VALUE="9013300/1">6040198</MONSTER>
		<MONSTER OBJECTNO="1" TYPE="INCPARAM_IN" VALUE="9013300/1">6370100</MONSTER>
		<MONSTER OBJECTNO="1" TYPE="INCPARAM_IN" VALUE="9013300/1">6370101</MONSTER>
		<MONSTER OBJECTNO="1" TYPE="INCPARAM_IN" VALUE="9013300/1">6370106</MONSTER>
	</EVENTS>
	<OBJECTS TYPE="NOSTEP">
		<OBJECT1 COUNT="20" TEXT="518916"/>
		<OBJECT2 COUNT="0" TEXT="0"/>
		<OBJECT3 COUNT="0" TEXT="0"/>
		<OBJECT4 COUNT="0" TEXT="0"/>
		<OBJECT5 COUNT="0" TEXT="0"/>
	</OBJECTS>
	<REWARD>
		<SELECT1 COUNT="0">
			<ITEM COUNT="1">50900060</ITEM>
			<ITEM COUNT="3">51100350</ITEM>			
		</SELECT1>
	</REWARD>	
	<DIALOGS>
		<!--101번은 퀘스트 의뢰 정보창-->
		<!--MEMO=201번은 퀘스트 수락/거부 여부창-->
		<DIALOG ID="101" TYPE="PROLOG">
			<BODY TEXT="518910" FACE="Jess_normal"/>
			<SELECT ID="10000" TYPE="ACCEPT" TEXT="500004">수락</SELECT>
			<SELECT ID="20000" TYPE="REJECT" TEXT="500005">거절</SELECT>
		</DIALOG>
		<!--301번은 퀘스트 수락 하면 뜰창 있어도 되고 없어도 된다.-->
		<DIALOG ID="301">
			<BODY TEXT="518911" FACE="Jess_smile"/>
			<SELECT ID="0" TEXT="500003">닫기</SELECT>
		</DIALOG>
		<!--401번은 퀘스트 거부 하면 뜰창 있어도 되고 없어도 된다.-->
		<DIALOG ID="401">
			<BODY TEXT="518912" FACE="Jess_angly"/>
			<SELECT ID="0" TEXT="500003">닫기</SELECT>
		</DIALOG>
		<DIALOG ID="501">
			<BODY TEXT="518913" FACE="Jess_angly"/>
			<SELECT ID="0" TEXT="500003">닫기</SELECT>
		</DIALOG>
		<!--601번은 퀘스트 조건이 완료 되고 NPC를 클릭했을 때 뜰창-->
		<DIALOG ID="601" TYPE="COMPLETE">
			<BODY TEXT="518914" FACE="Jess_smile"/>
			<SELECT ID="30999" TYPE="COMPLETE" TEXT="500007">완료</SELECT>
		</DIALOG>
		<!--901번은 !!절대로!! 퀘스트 정보창, 퀘스트 목록에서 퀘스트를 클릭하면 뜨게 된다.-->
		<DIALOG ID="901" TYPE="INFO">
			<BODY TEXT="518915"/>
			<SELECT ID="0" TEXT="19933">포기</SELECT>
		</DIALOG>
		<!--902는 인벤이 꽉 찾을 때 오류 메시지-->
		<DIALOG ID="902">
			<BODY TEXT="502048"/>
			<SELECT ID="0" TEXT="500003">닫기</SELECT>
		</DIALOG>
		<DIALOG ID="903">
			<BODY TEXT="501835"/>
			<SELECT ID="0" TEXT="500003">닫기</SELECT>
		</DIALOG>
		<!--Dialog ID 903~999번 까지는 어떤용도로든 사용가능하다.-->
	</DIALOGS>
</QUEST>
